displaycli/__init__.py
displaycli/__main__.py
displaycli/cli.py
displaycli/manager.py
displaycli-1.0.0.dist-info/WHEEL
displaycli-1.0.0.dist-info/entry_points.txt
displaycli-1.0.0.dist-info/METADATA
displaycli-1.0.0.dist-info/RECORD
