Metadata-Version: 2.3
Name: displaycli
Version: 1.0.0
Summary: A CLI tool to manage display resolutions on macOS.
Author: Nercone
Author-email: Nercone <nercone@diamondgotcat.net>
License: MIT
Classifier: Programming Language :: Python :: 3
Classifier: License :: OSI Approved :: MIT License
Classifier: Operating System :: MacOS
Requires-Dist: nercone-modern
Requires-Dist: pyobjc
Requires-Python: >=3.8
